wsipc/__init__.py
wsipc/client.py
wsipc/enums.py
wsipc/server.py
wsipc/utils.py
wsipc-0.0.3.dist-info/LICENSE
wsipc-0.0.3.dist-info/WHEEL
wsipc-0.0.3.dist-info/METADATA
wsipc-0.0.3.dist-info/RECORD
