Metadata-Version: 2.1
Name: wsipc
Version: 0.0.3
Summary: Async Python IPC using WebSockets
Home-page: https://github.com/vcokltfre/wsipc
License: MIT
Author: vcokltfre
Author-email: vcokltfre@gmail.com
Requires-Python: >=3.8,<4.0
Classifier: License :: OSI Approved :: MIT License
Classifier: Programming Language :: Python :: 3
Classifier: Programming Language :: Python :: 3.10
Classifier: Programming Language :: Python :: 3.8
Classifier: Programming Language :: Python :: 3.9
Requires-Dist: aiohttp (>=3.8.1,<4.0.0)
Requires-Dist: pre-commit (>=2.17.0,<3.0.0)
Project-URL: Repository, https://github.com/vcokltfre/wsipc
